orchestration/__init__.py
orchestration/orchestrator.py
orchestration/task.py
orchestration-1.1.3.dist-info/METADATA
orchestration-1.1.3.dist-info/WHEEL
orchestration-1.1.3.dist-info/top_level.txt
orchestration-1.1.3.dist-info/RECORD
