Metadata-Version: 2.1
Name: orchestration
Version: 1.1.3
Summary: This Python script provides functionality to schedule and execute scripts based on cron expressions. It allows executing both bash and Python scripts and provides options to add script parameters and skip conditions.
Home-page: https://github.com/htazewell/orchestration
Author: Henry Tazewell
Author-email: htazewell@gmail.com
License: UNKNOWN
Platform: UNKNOWN
Requires-Dist: croniter
Requires-Dist: pytz
